evercas/__init__.py
evercas/evercas.py
evercas/utils.py
evercas-0.8.1.dist-info/WHEEL
evercas-0.8.1.dist-info/METADATA
evercas-0.8.1.dist-info/licenses/LICENSE.md
evercas-0.8.1.dist-info/RECORD
