Metadata-Version: 2.1
Name: evercas
Version: 0.8.1
Summary: Cloneable (with rclone) content-addressable storage for Python
License: MIT
Keywords: evercas hash file system content addressable fixed storage
Author-email: Weedon & Scott Studios <Studios@WeedonAndScott.com>
Requires-Python: >=3.10
Classifier: Development Status :: 3 - Alpha
Classifier: Intended Audience :: Developers
Classifier: License :: OSI Approved :: MIT License
Classifier: Operating System :: OS Independent
Classifier: Programming Language :: Python :: 3
Classifier: Programming Language :: Python :: 3.10
Classifier: Topic :: Software Development :: Libraries
Classifier: Topic :: Software Development :: Libraries :: Python Modules
Classifier: Topic :: System :: Filesystems
Project-URL: Homepage, https://github.com/weedonandscott/evercas
